tcn/__init__.py
tcn/tcn.py
keras_tcn-3.5.5.dist-info/METADATA
keras_tcn-3.5.5.dist-info/WHEEL
keras_tcn-3.5.5.dist-info/top_level.txt
keras_tcn-3.5.5.dist-info/RECORD
