Metadata-Version: 2.2
Name: keras-tcn
Version: 3.5.5
Summary: Keras TCN
Author: Philippe Remy
Requires-Dist: numpy
Requires-Dist: tensorflow
Dynamic: author
Dynamic: description
Dynamic: description-content-type
Dynamic: requires-dist
Dynamic: summary
